start.py
exchanges_tests/__init__.py
exchanges_tests/abstract_authenticated_exchange_tester.py
exchanges_tests/abstract_authenticated_future_exchange_tester.py
exchanges_tests/test_ascendex.py
exchanges_tests/test_binance.py
exchanges_tests/test_bitget.py
exchanges_tests/test_bybit.py
exchanges_tests/test_bybit_futures.py
exchanges_tests/test_coinbase.py
exchanges_tests/test_cryptocom.py
exchanges_tests/test_hollaex.py
exchanges_tests/test_huobi.py
exchanges_tests/test_kucoin.py
exchanges_tests/test_kucoin_futures.py
exchanges_tests/test_okx.py
exchanges_tests/test_okx_futures.py
exchanges_tests/test_phemex.py
octobot/__init__.py
octobot/cli.py
octobot/commands.py
octobot/configuration_manager.cp38-win_amd64.pyd
octobot/configuration_manager.py
octobot/constants.py
octobot/databases_util.py
octobot/disclaimer.py
octobot/enums.py
octobot/errors.py
octobot/initializer.cp38-win_amd64.pyd
octobot/initializer.py
octobot/limits.py
octobot/logger.py
octobot/octobot.cp38-win_amd64.pyd
octobot/octobot.py
octobot/octobot_api.cp38-win_amd64.pyd
octobot/octobot_api.py
octobot/octobot_backtesting_factory.cp38-win_amd64.pyd
octobot/octobot_backtesting_factory.py
octobot/octobot_channel_consumer.cp38-win_amd64.pyd
octobot/octobot_channel_consumer.py
octobot/task_manager.cp38-win_amd64.pyd
octobot/task_manager.py
octobot/api/__init__.py
octobot/api/backtesting.py
octobot/api/strategy_optimizer.py
octobot/api/updater.py
octobot/automation/__init__.py
octobot/automation/automation.py
octobot/automation/bases/__init__.py
octobot/automation/bases/abstract_action.py
octobot/automation/bases/abstract_condition.py
octobot/automation/bases/abstract_trigger_event.py
octobot/automation/bases/automation_step.py
octobot/backtesting/__init__.py
octobot/backtesting/abstract_backtesting_test.cp38-win_amd64.pyd
octobot/backtesting/abstract_backtesting_test.py
octobot/backtesting/independent_backtesting.cp38-win_amd64.pyd
octobot/backtesting/independent_backtesting.py
OctoBot-0.4.49.dist-info/LICENSE
OctoBot-0.4.49.dist-info/METADATA
OctoBot-0.4.49.dist-info/WHEEL
OctoBot-0.4.49.dist-info/entry_points.txt
OctoBot-0.4.49.dist-info/top_level.txt
OctoBot-0.4.49.dist-info/RECORD
