Metadata-Version: 2.1
Name: OctoBot
Version: 0.4.49
Summary: Cryptocurrencies alert / trading bot
Home-page: https://github.com/Drakkar-Software/OctoBot
Author: Drakkar-Software
Author-email: drakkar-software@protonmail.com
License: GPL-3.0
Classifier: Development Status :: 4 - Beta
Classifier: Operating System :: OS Independent
Classifier: Operating System :: MacOS :: MacOS X
Classifier: Operating System :: Microsoft :: Windows
Classifier: Operating System :: POSIX
Classifier: Programming Language :: Python :: 3.8
Classifier: Programming Language :: Cython
Requires-Python: >=3.8
License-File: LICENSE
Requires-Dist: cython (==0.29.32)
Requires-Dist: OctoBot-Commons (==1.8.27)
Requires-Dist: OctoBot-Trading (==2.3.37)
Requires-Dist: OctoBot-Evaluators (==1.8.7)
Requires-Dist: OctoBot-Tentacles-Manager (==2.8.6)
Requires-Dist: OctoBot-Services (==1.5.5)
Requires-Dist: OctoBot-Backtesting (==1.8.2)
Requires-Dist: Async-Channel (==2.1.0)
Requires-Dist: trading-backend (==1.0.19)
Requires-Dist: colorlog (==4.7.2)
Requires-Dist: yarl (==1.7.2)
Requires-Dist: idna (<2.9,>=2.5)
Requires-Dist: requests (==2.25.1)
Requires-Dist: packaging (==21.3)
Requires-Dist: python-dotenv (==0.21.0)
Requires-Dist: setuptools (<65.6)
Requires-Dist: websockets
Requires-Dist: gmqtt (==0.6.11)
Requires-Dist: supabase (==1.0.3)
